aiger/__init__.py
aiger/aig.py
aiger/common.py
aiger/expr.py
aiger/hypothesis.py
aiger/immutable.py
aiger/lazy.py
aiger/parser.py
aiger/writer.py
py_aiger-8.1.0.dist-info/WHEEL
py_aiger-8.1.0.dist-info/METADATA
py_aiger-8.1.0.dist-info/RECORD
