Metadata-Version: 2.4
Name: py-aiger
Version: 8.1.0
Summary: A python library for manipulating sequential and-inverter gates.
Author: Marcell Vazquez-Chanlatte
Author-email: Marcell Vazquez-Chanlatte <marcell.vc@eecs.berkeley.edu>
License-Expression: MIT
Requires-Dist: attrs>=23
Requires-Dist: bidict>=0.22.0,<1
Requires-Dist: funcy>=2,<3
Requires-Dist: pyrsistent>=0.19.0,<1
Requires-Dist: sortedcontainers>=2.3.0,<3
Requires-Python: >=3.11, <4
Project-URL: Repository, https://github.com/mvcisback/py-aiger
